example/__init__.py
example/app.py
example/scheduler_worker.py
example/web_app.py
flask_scheduler_manager/__init__.py
flask_scheduler_manager/manager.py
flask_scheduler_manager/migrations.py
flask_scheduler_manager/models.py
flask_scheduler_manager/redis_stream.py
flask_scheduler_manager-1.0.0.dist-info/LICENSE
flask_scheduler_manager-1.0.0.dist-info/METADATA
flask_scheduler_manager-1.0.0.dist-info/WHEEL
flask_scheduler_manager-1.0.0.dist-info/top_level.txt
flask_scheduler_manager-1.0.0.dist-info/RECORD
