Metadata-Version: 2.1
Name: flask-scheduler-manager
Version: 1.0.0
Summary: 基于Flask SQLAlchemy和flask_apscheduler的动态定时任务管理系统
Home-page: https://github.com/BingerYang/flask-scheduler-manager
Author: binger
Author-email: xuehen_521@126.com
Classifier: Development Status :: 4 - Beta
Classifier: Intended Audience :: Developers
Classifier: Topic :: Software Development :: Libraries :: Python Modules
Classifier: License :: OSI Approved :: MIT License
Classifier: Programming Language :: Python :: 3
Classifier: Programming Language :: Python :: 3.7
Classifier: Programming Language :: Python :: 3.8
Classifier: Programming Language :: Python :: 3.9
Classifier: Programming Language :: Python :: 3.10
Classifier: Programming Language :: Python :: 3.11
Requires-Python: >=3.7
License-File: LICENSE
Requires-Dist: Flask (>=2.0.0)
Requires-Dist: SQLAlchemy (>=1.4.0)
Requires-Dist: flask-sqlalchemy (>=2.5.0)
Requires-Dist: flask-apscheduler (>=1.12.0)
Requires-Dist: APScheduler (>=3.10.0)
Requires-Dist: redis (>=4.5.0)
